src/main.py
src/api/__init__.py
src/api/deps.py
src/api/v1/__init__.py
src/api/v1/endpoints/__init__.py
src/api/v1/endpoints/admin.py
src/api/v1/endpoints/audio.py
src/api/v1/endpoints/auth.py
src/api/v1/endpoints/billing.py
src/api/v1/endpoints/chat.py
src/api/v1/endpoints/connectors.py
src/api/v1/endpoints/diagnostic.py
src/api/v1/endpoints/ingestion.py
src/api/v1/endpoints/integrations.py
src/api/v1/endpoints/logs.py
src/api/v1/endpoints/organization.py
src/api/v1/endpoints/search.py
src/api/v1/endpoints/stats.py
src/api/v1/endpoints/tasks.py
src/api/v1/endpoints/traces.py
src/api/v1/endpoints/webhooks.py
src/core/__init__.py
src/core/auth.py
src/core/config.py
src/core/entitlements.py
src/core/limiter.py
src/core/logging_utils.py
src/core/middleware.py
src/core/tier_limits.py
src/core/rag/__init__.py
src/core/rag/base.py
src/core/rag/pipeline.py
src/core/rag/presets.py
src/core/rag/chunking/__init__.py
src/core/rag/chunking/recursive.py
src/core/rag/chunking/semantic.py
src/core/rag/retrieval/__init__.py
src/core/rag/retrieval/hybrid.py
src/db/__init__.py
src/db/session.py
src/models/__init__.py
src/models/audio.py
src/models/auth.py
src/models/connector.py
src/models/entitlements.py
src/models/log.py
src/models/trace.py
src/models/transcript.py
src/models/webhook.py
src/services/__init__.py
src/services/audio_service.py
src/services/connector.py
src/services/embedding.py
src/services/entitlement_service.py
src/services/ingestion.py
src/services/queue.py
src/services/search.py
src/services/storage.py
src/services/stripe_service.py
src/services/trace.py
src/services/transcription.py
src/services/usage_service.py
src/services/webhook_dispatcher.py
src/utils/__init__.py
epist-1.2.2.dist-info/METADATA
epist-1.2.2.dist-info/WHEEL
epist-1.2.2.dist-info/RECORD
