Metadata-Version: 2.4
Name: epist
Version: 1.2.2
Summary: Audio-First Knowledge Engine Platform
Requires-Python: >=3.11
Requires-Dist: alembic>=1.13.0
Requires-Dist: apscheduler>=3.10.0
Requires-Dist: asyncpg>=0.29.0
Requires-Dist: chromadb>=0.4.0
Requires-Dist: fastapi>=0.109.0
Requires-Dist: feedparser>=6.0.0
Requires-Dist: firebase-admin>=6.2.0
Requires-Dist: fireworks-ai>=0.11.0
Requires-Dist: google-cloud-storage>=2.14.0
Requires-Dist: google-cloud-tasks
Requires-Dist: greenlet
Requires-Dist: httpx>=0.26.0
Requires-Dist: langchain-community>=0.3.27
Requires-Dist: langchain-core>=0.3.0
Requires-Dist: langchain-experimental>=0.0.49
Requires-Dist: langchain-openai>=0.0.8
Requires-Dist: langchain>=0.1.0
Requires-Dist: mcp>=1.23.0
Requires-Dist: moviepy>=1.0.3
Requires-Dist: openai>=1.12.0
Requires-Dist: pgvector>=0.2.4
Requires-Dist: protobuf>=5.29.5
Requires-Dist: pydantic-settings>=2.1.0
Requires-Dist: pydantic>=2.6.0
Requires-Dist: pydub>=0.25.1
Requires-Dist: python-multipart>=0.0.9
Requires-Dist: rank-bm25>=0.2.2
Requires-Dist: sentence-transformers>=2.2.2
Requires-Dist: sentry-sdk[fastapi]>=1.40.0
Requires-Dist: slowapi>=0.1.9
Requires-Dist: sqlmodel>=0.0.14
Requires-Dist: stripe>=14.0.1
Requires-Dist: tenacity>=8.2.3
Requires-Dist: urllib3>=2.6.0
Requires-Dist: uvicorn[standard]>=0.27.0
Provides-Extra: audio-rag
Requires-Dist: laion-clap>=0.0.16; extra == 'audio-rag'
Requires-Dist: librosa>=0.10.1; extra == 'audio-rag'
Requires-Dist: numpy>=1.26.0; extra == 'audio-rag'
Requires-Dist: torch==2.5.1; extra == 'audio-rag'
Requires-Dist: torchaudio==2.5.1; extra == 'audio-rag'
Requires-Dist: torchvision==0.20.1; extra == 'audio-rag'
Requires-Dist: transformers>=4.30.0; extra == 'audio-rag'
Provides-Extra: dev
Requires-Dist: aiosqlite; extra == 'dev'
Requires-Dist: httpx; extra == 'dev'
Requires-Dist: mypy>=1.0.0; extra == 'dev'
Requires-Dist: pre-commit>=3.6.0; extra == 'dev'
Requires-Dist: pytest; extra == 'dev'
Requires-Dist: pytest-asyncio>=0.23.0; extra == 'dev'
Requires-Dist: pytest>=8.0.0; extra == 'dev'
Requires-Dist: ruff>=0.2.0; extra == 'dev'
Requires-Dist: types-requests; extra == 'dev'
Provides-Extra: lab
Requires-Dist: arize-phoenix>=4.0.0; extra == 'lab'
Requires-Dist: datasets>=2.14.0; extra == 'lab'
Requires-Dist: matplotlib>=3.8.0; extra == 'lab'
Requires-Dist: networkx>=3.0; extra == 'lab'
Requires-Dist: pandas>=2.0.0; extra == 'lab'
Requires-Dist: ragas>=0.1.0; extra == 'lab'
